[{"arguments":["clang","-Wno-documentation-unknown-command","-Wno-unknown-warning-option","-Wno-unknown-pragmas","-nostdinc","-nostdinc++","-DQT_QML_DEBUG","-g","-std=gnu++17","-fdiagnostics-color=always","-fsyntax-only","-m64","--target=x86_64-w64-mingw32","-DMINGW_HAS_SECURE_API","-DQT_CORE_LIB","-DQT_GUI_LIB","-DQT_NEEDS_QMAIN","-DQT_SQL_LIB","-DQT_WIDGETS_LIB","-DUNICODE","-DWIN32","-DWIN64","-D_ENABLE_EXTENDED_ALIGNED_STORAGE","-D_UNICODE","-D_WIN64","-DQ_CREATOR_RUN","-DQT_ANNOTATE_FUNCTION(x)=__attribute__((annotate(#x)))","-IC:\\Qt\\Tools\\QtCreator\\share\\qtcreator\\cplusplus\\wrappedMingwHeaders","-IC:\\Qt\\Tools\\QtCreator\\share\\qtcreator\\cplusplus\\wrappedQtHeaders","-IC:\\Qt\\Tools\\QtCreator\\share\\qtcreator\\cplusplus\\wrappedQtHeaders\\QtCore","-ID:\\Projects\\QFinance2\\build\\Desktop_Qt_6_9_3_MinGW_64_bit-Debug\\QFinance2_autogen\\include","-isystem","C:\\Qt\\6.9.3\\mingw_64\\include\\QtCore","-isystem","C:\\Qt\\6.9.3\\mingw_64\\include","-isystem","C:\\Qt\\6.9.3\\mingw_64\\mkspecs\\win32-g++","-isystem","C:\\Qt\\6.9.3\\mingw_64\\include\\QtWidgets","-isystem","C:\\Qt\\6.9.3\\mingw_64\\include\\QtGui","-isystem","C:\\Qt\\6.9.3\\mingw_64\\include\\QtSql","-isystem","C:\\Qt\\Tools\\mingw1310_64\\lib\\gcc\\x86_64-w64-mingw32\\13.1.0\\include\\c++","-isystem","C:\\Qt\\Tools\\mingw1310_64\\lib\\gcc\\x86_64-w64-mingw32\\13.1.0\\include\\c++\\x86_64-w64-mingw32","-isystem","C:\\Qt\\Tools\\mingw1310_64\\lib\\gcc\\x86_64-w64-mingw32\\13.1.0\\include\\c++\\backward","-isystem","C:\\Qt\\Tools\\QtCreator\\bin\\clang\\lib\\clang\\20\\include","-isystem","C:\\Qt\\Tools\\mingw1310_64\\x86_64-w64-mingw32\\include","-fmessage-length=0","-fdiagnostics-show-note-include-stack","-fretain-comments-from-system-headers","-fmacro-backtrace-limit=0","-ferror-limit=1000","-x","c++","D:\\Projects\\QFinance2\\main.cpp"],"directory":"D:/Projects/QFinance2/build/Desktop_Qt_6_9_3_MinGW_64_bit-Debug/.qtc_clangd","file":"D:/Projects/QFinance2/main.cpp"},{"arguments":["clang","-Wno-documentation-unknown-command","-Wno-unknown-warning-option","-Wno-unknown-pragmas","-nostdinc","-nostdinc++","-DQT_QML_DEBUG","-g","-std=gnu++17","-fdiagnostics-color=always","-fsyntax-only","-m64","--target=x86_64-w64-mingw32","-DMINGW_HAS_SECURE_API","-DQT_CORE_LIB","-DQT_GUI_LIB","-DQT_NEEDS_QMAIN","-DQT_SQL_LIB","-DQT_WIDGETS_LIB","-DUNICODE","-DWIN32","-DWIN64","-D_ENABLE_EXTENDED_ALIGNED_STORAGE","-D_UNICODE","-D_WIN64","-DQ_CREATOR_RUN","-DQT_ANNOTATE_FUNCTION(x)=__attribute__((annotate(#x)))","-IC:\\Qt\\Tools\\QtCreator\\share\\qtcreator\\cplusplus\\wrappedMingwHeaders","-IC:\\Qt\\Tools\\QtCreator\\share\\qtcreator\\cplusplus\\wrappedQtHeaders","-IC:\\Qt\\Tools\\QtCreator\\share\\qtcreator\\cplusplus\\wrappedQtHeaders\\QtCore","-ID:\\Projects\\QFinance2\\build\\Desktop_Qt_6_9_3_MinGW_64_bit-Debug\\QFinance2_autogen\\include","-isystem","C:\\Qt\\6.9.3\\mingw_64\\include\\QtCore","-isystem","C:\\Qt\\6.9.3\\mingw_64\\include","-isystem","C:\\Qt\\6.9.3\\mingw_64\\mkspecs\\win32-g++","-isystem","C:\\Qt\\6.9.3\\mingw_64\\include\\QtWidgets","-isystem","C:\\Qt\\6.9.3\\mingw_64\\include\\QtGui","-isystem","C:\\Qt\\6.9.3\\mingw_64\\include\\QtSql","-isystem","C:\\Qt\\Tools\\mingw1310_64\\lib\\gcc\\x86_64-w64-mingw32\\13.1.0\\include\\c++","-isystem","C:\\Qt\\Tools\\mingw1310_64\\lib\\gcc\\x86_64-w64-mingw32\\13.1.0\\include\\c++\\x86_64-w64-mingw32","-isystem","C:\\Qt\\Tools\\mingw1310_64\\lib\\gcc\\x86_64-w64-mingw32\\13.1.0\\include\\c++\\backward","-isystem","C:\\Qt\\Tools\\QtCreator\\bin\\clang\\lib\\clang\\20\\include","-isystem","C:\\Qt\\Tools\\mingw1310_64\\x86_64-w64-mingw32\\include","-fmessage-length=0","-fdiagnostics-show-note-include-stack","-fretain-comments-from-system-headers","-fmacro-backtrace-limit=0","-ferror-limit=1000","-x","c++","D:\\Projects\\QFinance2\\mainwindow.cpp"],"directory":"D:/Projects/QFinance2/build/Desktop_Qt_6_9_3_MinGW_64_bit-Debug/.qtc_clangd","file":"D:/Projects/QFinance2/mainwindow.cpp"},{"arguments":["clang","-Wno-documentation-unknown-command","-Wno-unknown-warning-option","-Wno-unknown-pragmas","-nostdinc","-nostdinc++","-DQT_QML_DEBUG","-g","-std=gnu++17","-fdiagnostics-color=always","-fsyntax-only","-m64","--target=x86_64-w64-mingw32","-DMINGW_HAS_SECURE_API","-DQT_CORE_LIB","-DQT_GUI_LIB","-DQT_NEEDS_QMAIN","-DQT_SQL_LIB","-DQT_WIDGETS_LIB","-DUNICODE","-DWIN32","-DWIN64","-D_ENABLE_EXTENDED_ALIGNED_STORAGE","-D_UNICODE","-D_WIN64","-DQ_CREATOR_RUN","-DQT_ANNOTATE_FUNCTION(x)=__attribute__((annotate(#x)))","-IC:\\Qt\\Tools\\QtCreator\\share\\qtcreator\\cplusplus\\wrappedMingwHeaders","-IC:\\Qt\\Tools\\QtCreator\\share\\qtcreator\\cplusplus\\wrappedQtHeaders","-IC:\\Qt\\Tools\\QtCreator\\share\\qtcreator\\cplusplus\\wrappedQtHeaders\\QtCore","-ID:\\Projects\\QFinance2\\build\\Desktop_Qt_6_9_3_MinGW_64_bit-Debug\\QFinance2_autogen\\include","-isystem","C:\\Qt\\6.9.3\\mingw_64\\include\\QtCore","-isystem","C:\\Qt\\6.9.3\\mingw_64\\include","-isystem","C:\\Qt\\6.9.3\\mingw_64\\mkspecs\\win32-g++","-isystem","C:\\Qt\\6.9.3\\mingw_64\\include\\QtWidgets","-isystem","C:\\Qt\\6.9.3\\mingw_64\\include\\QtGui","-isystem","C:\\Qt\\6.9.3\\mingw_64\\include\\QtSql","-isystem","C:\\Qt\\Tools\\mingw1310_64\\lib\\gcc\\x86_64-w64-mingw32\\13.1.0\\include\\c++","-isystem","C:\\Qt\\Tools\\mingw1310_64\\lib\\gcc\\x86_64-w64-mingw32\\13.1.0\\include\\c++\\x86_64-w64-mingw32","-isystem","C:\\Qt\\Tools\\mingw1310_64\\lib\\gcc\\x86_64-w64-mingw32\\13.1.0\\include\\c++\\backward","-isystem","C:\\Qt\\Tools\\QtCreator\\bin\\clang\\lib\\clang\\20\\include","-isystem","C:\\Qt\\Tools\\mingw1310_64\\x86_64-w64-mingw32\\include","-fmessage-length=0","-fdiagnostics-show-note-include-stack","-fretain-comments-from-system-headers","-fmacro-backtrace-limit=0","-ferror-limit=1000","-x","c++","D:\\Projects\\QFinance2\\database\\databasemanager.cpp"],"directory":"D:/Projects/QFinance2/build/Desktop_Qt_6_9_3_MinGW_64_bit-Debug/.qtc_clangd","file":"D:/Projects/QFinance2/database/databasemanager.cpp"},{"arguments":["clang","-Wno-documentation-unknown-command","-Wno-unknown-warning-option","-Wno-unknown-pragmas","-nostdinc","-nostdinc++","-DQT_QML_DEBUG","-g","-std=gnu++17","-fdiagnostics-color=always","-fsyntax-only","-m64","--target=x86_64-w64-mingw32","-DMINGW_HAS_SECURE_API","-DQT_CORE_LIB","-DQT_GUI_LIB","-DQT_NEEDS_QMAIN","-DQT_SQL_LIB","-DQT_WIDGETS_LIB","-DUNICODE","-DWIN32","-DWIN64","-D_ENABLE_EXTENDED_ALIGNED_STORAGE","-D_UNICODE","-D_WIN64","-DQ_CREATOR_RUN","-DQT_ANNOTATE_FUNCTION(x)=__attribute__((annotate(#x)))","-IC:\\Qt\\Tools\\QtCreator\\share\\qtcreator\\cplusplus\\wrappedMingwHeaders","-IC:\\Qt\\Tools\\QtCreator\\share\\qtcreator\\cplusplus\\wrappedQtHeaders","-IC:\\Qt\\Tools\\QtCreator\\share\\qtcreator\\cplusplus\\wrappedQtHeaders\\QtCore","-ID:\\Projects\\QFinance2\\build\\Desktop_Qt_6_9_3_MinGW_64_bit-Debug\\QFinance2_autogen\\include","-isystem","C:\\Qt\\6.9.3\\mingw_64\\include\\QtCore","-isystem","C:\\Qt\\6.9.3\\mingw_64\\include","-isystem","C:\\Qt\\6.9.3\\mingw_64\\mkspecs\\win32-g++","-isystem","C:\\Qt\\6.9.3\\mingw_64\\include\\QtWidgets","-isystem","C:\\Qt\\6.9.3\\mingw_64\\include\\QtGui","-isystem","C:\\Qt\\6.9.3\\mingw_64\\include\\QtSql","-isystem","C:\\Qt\\Tools\\mingw1310_64\\lib\\gcc\\x86_64-w64-mingw32\\13.1.0\\include\\c++","-isystem","C:\\Qt\\Tools\\mingw1310_64\\lib\\gcc\\x86_64-w64-mingw32\\13.1.0\\include\\c++\\x86_64-w64-mingw32","-isystem","C:\\Qt\\Tools\\mingw1310_64\\lib\\gcc\\x86_64-w64-mingw32\\13.1.0\\include\\c++\\backward","-isystem","C:\\Qt\\Tools\\QtCreator\\bin\\clang\\lib\\clang\\20\\include","-isystem","C:\\Qt\\Tools\\mingw1310_64\\x86_64-w64-mingw32\\include","-fmessage-length=0","-fdiagnostics-show-note-include-stack","-fretain-comments-from-system-headers","-fmacro-backtrace-limit=0","-ferror-limit=1000","-x","c++","D:\\Projects\\QFinance2\\model\\utilisateur.cpp"],"directory":"D:/Projects/QFinance2/build/Desktop_Qt_6_9_3_MinGW_64_bit-Debug/.qtc_clangd","file":"D:/Projects/QFinance2/model/utilisateur.cpp"},{"arguments":["clang","-Wno-documentation-unknown-command","-Wno-unknown-warning-option","-Wno-unknown-pragmas","-nostdinc","-nostdinc++","-DQT_QML_DEBUG","-g","-std=gnu++17","-fdiagnostics-color=always","-fsyntax-only","-m64","--target=x86_64-w64-mingw32","-DMINGW_HAS_SECURE_API","-DQT_CORE_LIB","-DQT_GUI_LIB","-DQT_NEEDS_QMAIN","-DQT_SQL_LIB","-DQT_WIDGETS_LIB","-DUNICODE","-DWIN32","-DWIN64","-D_ENABLE_EXTENDED_ALIGNED_STORAGE","-D_UNICODE","-D_WIN64","-DQ_CREATOR_RUN","-DQT_ANNOTATE_FUNCTION(x)=__attribute__((annotate(#x)))","-IC:\\Qt\\Tools\\QtCreator\\share\\qtcreator\\cplusplus\\wrappedMingwHeaders","-IC:\\Qt\\Tools\\QtCreator\\share\\qtcreator\\cplusplus\\wrappedQtHeaders","-IC:\\Qt\\Tools\\QtCreator\\share\\qtcreator\\cplusplus\\wrappedQtHeaders\\QtCore","-ID:\\Projects\\QFinance2\\build\\Desktop_Qt_6_9_3_MinGW_64_bit-Debug\\QFinance2_autogen\\include","-isystem","C:\\Qt\\6.9.3\\mingw_64\\include\\QtCore","-isystem","C:\\Qt\\6.9.3\\mingw_64\\include","-isystem","C:\\Qt\\6.9.3\\mingw_64\\mkspecs\\win32-g++","-isystem","C:\\Qt\\6.9.3\\mingw_64\\include\\QtWidgets","-isystem","C:\\Qt\\6.9.3\\mingw_64\\include\\QtGui","-isystem","C:\\Qt\\6.9.3\\mingw_64\\include\\QtSql","-isystem","C:\\Qt\\Tools\\mingw1310_64\\lib\\gcc\\x86_64-w64-mingw32\\13.1.0\\include\\c++","-isystem","C:\\Qt\\Tools\\mingw1310_64\\lib\\gcc\\x86_64-w64-mingw32\\13.1.0\\include\\c++\\x86_64-w64-mingw32","-isystem","C:\\Qt\\Tools\\mingw1310_64\\lib\\gcc\\x86_64-w64-mingw32\\13.1.0\\include\\c++\\backward","-isystem","C:\\Qt\\Tools\\QtCreator\\bin\\clang\\lib\\clang\\20\\include","-isystem","C:\\Qt\\Tools\\mingw1310_64\\x86_64-w64-mingw32\\include","-fmessage-length=0","-fdiagnostics-show-note-include-stack","-fretain-comments-from-system-headers","-fmacro-backtrace-limit=0","-ferror-limit=1000","-x","c++","D:\\Projects\\QFinance2\\model\\compte.cpp"],"directory":"D:/Projects/QFinance2/build/Desktop_Qt_6_9_3_MinGW_64_bit-Debug/.qtc_clangd","file":"D:/Projects/QFinance2/model/compte.cpp"},{"arguments":["clang","-Wno-documentation-unknown-command","-Wno-unknown-warning-option","-Wno-unknown-pragmas","-nostdinc","-nostdinc++","-DQT_QML_DEBUG","-g","-std=gnu++17","-fdiagnostics-color=always","-fsyntax-only","-m64","--target=x86_64-w64-mingw32","-DMINGW_HAS_SECURE_API","-DQT_CORE_LIB","-DQT_GUI_LIB","-DQT_NEEDS_QMAIN","-DQT_SQL_LIB","-DQT_WIDGETS_LIB","-DUNICODE","-DWIN32","-DWIN64","-D_ENABLE_EXTENDED_ALIGNED_STORAGE","-D_UNICODE","-D_WIN64","-DQ_CREATOR_RUN","-DQT_ANNOTATE_FUNCTION(x)=__attribute__((annotate(#x)))","-IC:\\Qt\\Tools\\QtCreator\\share\\qtcreator\\cplusplus\\wrappedMingwHeaders","-IC:\\Qt\\Tools\\QtCreator\\share\\qtcreator\\cplusplus\\wrappedQtHeaders","-IC:\\Qt\\Tools\\QtCreator\\share\\qtcreator\\cplusplus\\wrappedQtHeaders\\QtCore","-ID:\\Projects\\QFinance2\\build\\Desktop_Qt_6_9_3_MinGW_64_bit-Debug\\QFinance2_autogen\\include","-isystem","C:\\Qt\\6.9.3\\mingw_64\\include\\QtCore","-isystem","C:\\Qt\\6.9.3\\mingw_64\\include","-isystem","C:\\Qt\\6.9.3\\mingw_64\\mkspecs\\win32-g++","-isystem","C:\\Qt\\6.9.3\\mingw_64\\include\\QtWidgets","-isystem","C:\\Qt\\6.9.3\\mingw_64\\include\\QtGui","-isystem","C:\\Qt\\6.9.3\\mingw_64\\include\\QtSql","-isystem","C:\\Qt\\Tools\\mingw1310_64\\lib\\gcc\\x86_64-w64-mingw32\\13.1.0\\include\\c++","-isystem","C:\\Qt\\Tools\\mingw1310_64\\lib\\gcc\\x86_64-w64-mingw32\\13.1.0\\include\\c++\\x86_64-w64-mingw32","-isystem","C:\\Qt\\Tools\\mingw1310_64\\lib\\gcc\\x86_64-w64-mingw32\\13.1.0\\include\\c++\\backward","-isystem","C:\\Qt\\Tools\\QtCreator\\bin\\clang\\lib\\clang\\20\\include","-isystem","C:\\Qt\\Tools\\mingw1310_64\\x86_64-w64-mingw32\\include","-fmessage-length=0","-fdiagnostics-show-note-include-stack","-fretain-comments-from-system-headers","-fmacro-backtrace-limit=0","-ferror-limit=1000","-x","c++","D:\\Projects\\QFinance2\\model\\comptecourant.cpp"],"directory":"D:/Projects/QFinance2/build/Desktop_Qt_6_9_3_MinGW_64_bit-Debug/.qtc_clangd","file":"D:/Projects/QFinance2/model/comptecourant.cpp"},{"arguments":["clang","-Wno-documentation-unknown-command","-Wno-unknown-warning-option","-Wno-unknown-pragmas","-nostdinc","-nostdinc++","-DQT_QML_DEBUG","-g","-std=gnu++17","-fdiagnostics-color=always","-fsyntax-only","-m64","--target=x86_64-w64-mingw32","-DMINGW_HAS_SECURE_API","-DQT_CORE_LIB","-DQT_GUI_LIB","-DQT_NEEDS_QMAIN","-DQT_SQL_LIB","-DQT_WIDGETS_LIB","-DUNICODE","-DWIN32","-DWIN64","-D_ENABLE_EXTENDED_ALIGNED_STORAGE","-D_UNICODE","-D_WIN64","-DQ_CREATOR_RUN","-DQT_ANNOTATE_FUNCTION(x)=__attribute__((annotate(#x)))","-IC:\\Qt\\Tools\\QtCreator\\share\\qtcreator\\cplusplus\\wrappedMingwHeaders","-IC:\\Qt\\Tools\\QtCreator\\share\\qtcreator\\cplusplus\\wrappedQtHeaders","-IC:\\Qt\\Tools\\QtCreator\\share\\qtcreator\\cplusplus\\wrappedQtHeaders\\QtCore","-ID:\\Projects\\QFinance2\\build\\Desktop_Qt_6_9_3_MinGW_64_bit-Debug\\QFinance2_autogen\\include","-isystem","C:\\Qt\\6.9.3\\mingw_64\\include\\QtCore","-isystem","C:\\Qt\\6.9.3\\mingw_64\\include","-isystem","C:\\Qt\\6.9.3\\mingw_64\\mkspecs\\win32-g++","-isystem","C:\\Qt\\6.9.3\\mingw_64\\include\\QtWidgets","-isystem","C:\\Qt\\6.9.3\\mingw_64\\include\\QtGui","-isystem","C:\\Qt\\6.9.3\\mingw_64\\include\\QtSql","-isystem","C:\\Qt\\Tools\\mingw1310_64\\lib\\gcc\\x86_64-w64-mingw32\\13.1.0\\include\\c++","-isystem","C:\\Qt\\Tools\\mingw1310_64\\lib\\gcc\\x86_64-w64-mingw32\\13.1.0\\include\\c++\\x86_64-w64-mingw32","-isystem","C:\\Qt\\Tools\\mingw1310_64\\lib\\gcc\\x86_64-w64-mingw32\\13.1.0\\include\\c++\\backward","-isystem","C:\\Qt\\Tools\\QtCreator\\bin\\clang\\lib\\clang\\20\\include","-isystem","C:\\Qt\\Tools\\mingw1310_64\\x86_64-w64-mingw32\\include","-fmessage-length=0","-fdiagnostics-show-note-include-stack","-fretain-comments-from-system-headers","-fmacro-backtrace-limit=0","-ferror-limit=1000","-x","c++","D:\\Projects\\QFinance2\\model\\compteepargne.cpp"],"directory":"D:/Projects/QFinance2/build/Desktop_Qt_6_9_3_MinGW_64_bit-Debug/.qtc_clangd","file":"D:/Projects/QFinance2/model/compteepargne.cpp"},{"arguments":["clang","-Wno-documentation-unknown-command","-Wno-unknown-warning-option","-Wno-unknown-pragmas","-nostdinc","-nostdinc++","-DQT_QML_DEBUG","-g","-std=gnu++17","-fdiagnostics-color=always","-fsyntax-only","-m64","--target=x86_64-w64-mingw32","-DMINGW_HAS_SECURE_API","-DQT_CORE_LIB","-DQT_GUI_LIB","-DQT_NEEDS_QMAIN","-DQT_SQL_LIB","-DQT_WIDGETS_LIB","-DUNICODE","-DWIN32","-DWIN64","-D_ENABLE_EXTENDED_ALIGNED_STORAGE","-D_UNICODE","-D_WIN64","-DQ_CREATOR_RUN","-DQT_ANNOTATE_FUNCTION(x)=__attribute__((annotate(#x)))","-IC:\\Qt\\Tools\\QtCreator\\share\\qtcreator\\cplusplus\\wrappedMingwHeaders","-IC:\\Qt\\Tools\\QtCreator\\share\\qtcreator\\cplusplus\\wrappedQtHeaders","-IC:\\Qt\\Tools\\QtCreator\\share\\qtcreator\\cplusplus\\wrappedQtHeaders\\QtCore","-ID:\\Projects\\QFinance2\\build\\Desktop_Qt_6_9_3_MinGW_64_bit-Debug\\QFinance2_autogen\\include","-isystem","C:\\Qt\\6.9.3\\mingw_64\\include\\QtCore","-isystem","C:\\Qt\\6.9.3\\mingw_64\\include","-isystem","C:\\Qt\\6.9.3\\mingw_64\\mkspecs\\win32-g++","-isystem","C:\\Qt\\6.9.3\\mingw_64\\include\\QtWidgets","-isystem","C:\\Qt\\6.9.3\\mingw_64\\include\\QtGui","-isystem","C:\\Qt\\6.9.3\\mingw_64\\include\\QtSql","-isystem","C:\\Qt\\Tools\\mingw1310_64\\lib\\gcc\\x86_64-w64-mingw32\\13.1.0\\include\\c++","-isystem","C:\\Qt\\Tools\\mingw1310_64\\lib\\gcc\\x86_64-w64-mingw32\\13.1.0\\include\\c++\\x86_64-w64-mingw32","-isystem","C:\\Qt\\Tools\\mingw1310_64\\lib\\gcc\\x86_64-w64-mingw32\\13.1.0\\include\\c++\\backward","-isystem","C:\\Qt\\Tools\\QtCreator\\bin\\clang\\lib\\clang\\20\\include","-isystem","C:\\Qt\\Tools\\mingw1310_64\\x86_64-w64-mingw32\\include","-fmessage-length=0","-fdiagnostics-show-note-include-stack","-fretain-comments-from-system-headers","-fmacro-backtrace-limit=0","-ferror-limit=1000","-x","c++","D:\\Projects\\QFinance2\\model\\transfert.cpp"],"directory":"D:/Projects/QFinance2/build/Desktop_Qt_6_9_3_MinGW_64_bit-Debug/.qtc_clangd","file":"D:/Projects/QFinance2/model/transfert.cpp"},{"arguments":["clang","-Wno-documentation-unknown-command","-Wno-unknown-warning-option","-Wno-unknown-pragmas","-nostdinc","-nostdinc++","-DQT_QML_DEBUG","-g","-std=gnu++17","-fdiagnostics-color=always","-fsyntax-only","-m64","--target=x86_64-w64-mingw32","-DMINGW_HAS_SECURE_API","-DQT_CORE_LIB","-DQT_GUI_LIB","-DQT_NEEDS_QMAIN","-DQT_SQL_LIB","-DQT_WIDGETS_LIB","-DUNICODE","-DWIN32","-DWIN64","-D_ENABLE_EXTENDED_ALIGNED_STORAGE","-D_UNICODE","-D_WIN64","-DQ_CREATOR_RUN","-DQT_ANNOTATE_FUNCTION(x)=__attribute__((annotate(#x)))","-IC:\\Qt\\Tools\\QtCreator\\share\\qtcreator\\cplusplus\\wrappedMingwHeaders","-IC:\\Qt\\Tools\\QtCreator\\share\\qtcreator\\cplusplus\\wrappedQtHeaders","-IC:\\Qt\\Tools\\QtCreator\\share\\qtcreator\\cplusplus\\wrappedQtHeaders\\QtCore","-ID:\\Projects\\QFinance2\\build\\Desktop_Qt_6_9_3_MinGW_64_bit-Debug\\QFinance2_autogen\\include","-isystem","C:\\Qt\\6.9.3\\mingw_64\\include\\QtCore","-isystem","C:\\Qt\\6.9.3\\mingw_64\\include","-isystem","C:\\Qt\\6.9.3\\mingw_64\\mkspecs\\win32-g++","-isystem","C:\\Qt\\6.9.3\\mingw_64\\include\\QtWidgets","-isystem","C:\\Qt\\6.9.3\\mingw_64\\include\\QtGui","-isystem","C:\\Qt\\6.9.3\\mingw_64\\include\\QtSql","-isystem","C:\\Qt\\Tools\\mingw1310_64\\lib\\gcc\\x86_64-w64-mingw32\\13.1.0\\include\\c++","-isystem","C:\\Qt\\Tools\\mingw1310_64\\lib\\gcc\\x86_64-w64-mingw32\\13.1.0\\include\\c++\\x86_64-w64-mingw32","-isystem","C:\\Qt\\Tools\\mingw1310_64\\lib\\gcc\\x86_64-w64-mingw32\\13.1.0\\include\\c++\\backward","-isystem","C:\\Qt\\Tools\\QtCreator\\bin\\clang\\lib\\clang\\20\\include","-isystem","C:\\Qt\\Tools\\mingw1310_64\\x86_64-w64-mingw32\\include","-fmessage-length=0","-fdiagnostics-show-note-include-stack","-fretain-comments-from-system-headers","-fmacro-backtrace-limit=0","-ferror-limit=1000","-x","c++","D:\\Projects\\QFinance2\\repository\\compterepository.cpp"],"directory":"D:/Projects/QFinance2/build/Desktop_Qt_6_9_3_MinGW_64_bit-Debug/.qtc_clangd","file":"D:/Projects/QFinance2/repository/compterepository.cpp"},{"arguments":["clang","-Wno-documentation-unknown-command","-Wno-unknown-warning-option","-Wno-unknown-pragmas","-nostdinc","-nostdinc++","-DQT_QML_DEBUG","-g","-std=gnu++17","-fdiagnostics-color=always","-fsyntax-only","-m64","--target=x86_64-w64-mingw32","-DMINGW_HAS_SECURE_API","-DQT_CORE_LIB","-DQT_GUI_LIB","-DQT_NEEDS_QMAIN","-DQT_SQL_LIB","-DQT_WIDGETS_LIB","-DUNICODE","-DWIN32","-DWIN64","-D_ENABLE_EXTENDED_ALIGNED_STORAGE","-D_UNICODE","-D_WIN64","-DQ_CREATOR_RUN","-DQT_ANNOTATE_FUNCTION(x)=__attribute__((annotate(#x)))","-IC:\\Qt\\Tools\\QtCreator\\share\\qtcreator\\cplusplus\\wrappedMingwHeaders","-IC:\\Qt\\Tools\\QtCreator\\share\\qtcreator\\cplusplus\\wrappedQtHeaders","-IC:\\Qt\\Tools\\QtCreator\\share\\qtcreator\\cplusplus\\wrappedQtHeaders\\QtCore","-ID:\\Projects\\QFinance2\\build\\Desktop_Qt_6_9_3_MinGW_64_bit-Debug\\QFinance2_autogen\\include","-isystem","C:\\Qt\\6.9.3\\mingw_64\\include\\QtCore","-isystem","C:\\Qt\\6.9.3\\mingw_64\\include","-isystem","C:\\Qt\\6.9.3\\mingw_64\\mkspecs\\win32-g++","-isystem","C:\\Qt\\6.9.3\\mingw_64\\include\\QtWidgets","-isystem","C:\\Qt\\6.9.3\\mingw_64\\include\\QtGui","-isystem","C:\\Qt\\6.9.3\\mingw_64\\include\\QtSql","-isystem","C:\\Qt\\Tools\\mingw1310_64\\lib\\gcc\\x86_64-w64-mingw32\\13.1.0\\include\\c++","-isystem","C:\\Qt\\Tools\\mingw1310_64\\lib\\gcc\\x86_64-w64-mingw32\\13.1.0\\include\\c++\\x86_64-w64-mingw32","-isystem","C:\\Qt\\Tools\\mingw1310_64\\lib\\gcc\\x86_64-w64-mingw32\\13.1.0\\include\\c++\\backward","-isystem","C:\\Qt\\Tools\\QtCreator\\bin\\clang\\lib\\clang\\20\\include","-isystem","C:\\Qt\\Tools\\mingw1310_64\\x86_64-w64-mingw32\\include","-fmessage-length=0","-fdiagnostics-show-note-include-stack","-fretain-comments-from-system-headers","-fmacro-backtrace-limit=0","-ferror-limit=1000","-x","c++","D:\\Projects\\QFinance2\\repository\\transfertrepository.cpp"],"directory":"D:/Projects/QFinance2/build/Desktop_Qt_6_9_3_MinGW_64_bit-Debug/.qtc_clangd","file":"D:/Projects/QFinance2/repository/transfertrepository.cpp"},{"arguments":["clang","-Wno-documentation-unknown-command","-Wno-unknown-warning-option","-Wno-unknown-pragmas","-nostdinc","-nostdinc++","-DQT_QML_DEBUG","-g","-std=gnu++17","-fdiagnostics-color=always","-fsyntax-only","-m64","--target=x86_64-w64-mingw32","-DMINGW_HAS_SECURE_API","-DQT_CORE_LIB","-DQT_GUI_LIB","-DQT_NEEDS_QMAIN","-DQT_SQL_LIB","-DQT_WIDGETS_LIB","-DUNICODE","-DWIN32","-DWIN64","-D_ENABLE_EXTENDED_ALIGNED_STORAGE","-D_UNICODE","-D_WIN64","-DQ_CREATOR_RUN","-DQT_ANNOTATE_FUNCTION(x)=__attribute__((annotate(#x)))","-IC:\\Qt\\Tools\\QtCreator\\share\\qtcreator\\cplusplus\\wrappedMingwHeaders","-IC:\\Qt\\Tools\\QtCreator\\share\\qtcreator\\cplusplus\\wrappedQtHeaders","-IC:\\Qt\\Tools\\QtCreator\\share\\qtcreator\\cplusplus\\wrappedQtHeaders\\QtCore","-ID:\\Projects\\QFinance2\\build\\Desktop_Qt_6_9_3_MinGW_64_bit-Debug\\QFinance2_autogen\\include","-isystem","C:\\Qt\\6.9.3\\mingw_64\\include\\QtCore","-isystem","C:\\Qt\\6.9.3\\mingw_64\\include","-isystem","C:\\Qt\\6.9.3\\mingw_64\\mkspecs\\win32-g++","-isystem","C:\\Qt\\6.9.3\\mingw_64\\include\\QtWidgets","-isystem","C:\\Qt\\6.9.3\\mingw_64\\include\\QtGui","-isystem","C:\\Qt\\6.9.3\\mingw_64\\include\\QtSql","-isystem","C:\\Qt\\Tools\\mingw1310_64\\lib\\gcc\\x86_64-w64-mingw32\\13.1.0\\include\\c++","-isystem","C:\\Qt\\Tools\\mingw1310_64\\lib\\gcc\\x86_64-w64-mingw32\\13.1.0\\include\\c++\\x86_64-w64-mingw32","-isystem","C:\\Qt\\Tools\\mingw1310_64\\lib\\gcc\\x86_64-w64-mingw32\\13.1.0\\include\\c++\\backward","-isystem","C:\\Qt\\Tools\\QtCreator\\bin\\clang\\lib\\clang\\20\\include","-isystem","C:\\Qt\\Tools\\mingw1310_64\\x86_64-w64-mingw32\\include","-fmessage-length=0","-fdiagnostics-show-note-include-stack","-fretain-comments-from-system-headers","-fmacro-backtrace-limit=0","-ferror-limit=1000","-x","c++","D:\\Projects\\QFinance2\\repository\\categorierepository.cpp"],"directory":"D:/Projects/QFinance2/build/Desktop_Qt_6_9_3_MinGW_64_bit-Debug/.qtc_clangd","file":"D:/Projects/QFinance2/repository/categorierepository.cpp"},{"arguments":["clang","-Wno-documentation-unknown-command","-Wno-unknown-warning-option","-Wno-unknown-pragmas","-nostdinc","-nostdinc++","-DQT_QML_DEBUG","-g","-std=gnu++17","-fdiagnostics-color=always","-fsyntax-only","-m64","--target=x86_64-w64-mingw32","-DMINGW_HAS_SECURE_API","-DQT_CORE_LIB","-DQT_GUI_LIB","-DQT_NEEDS_QMAIN","-DQT_SQL_LIB","-DQT_WIDGETS_LIB","-DUNICODE","-DWIN32","-DWIN64","-D_ENABLE_EXTENDED_ALIGNED_STORAGE","-D_UNICODE","-D_WIN64","-DQ_CREATOR_RUN","-DQT_ANNOTATE_FUNCTION(x)=__attribute__((annotate(#x)))","-IC:\\Qt\\Tools\\QtCreator\\share\\qtcreator\\cplusplus\\wrappedMingwHeaders","-IC:\\Qt\\Tools\\QtCreator\\share\\qtcreator\\cplusplus\\wrappedQtHeaders","-IC:\\Qt\\Tools\\QtCreator\\share\\qtcreator\\cplusplus\\wrappedQtHeaders\\QtCore","-ID:\\Projects\\QFinance2\\build\\Desktop_Qt_6_9_3_MinGW_64_bit-Debug\\QFinance2_autogen\\include","-isystem","C:\\Qt\\6.9.3\\mingw_64\\include\\QtCore","-isystem","C:\\Qt\\6.9.3\\mingw_64\\include","-isystem","C:\\Qt\\6.9.3\\mingw_64\\mkspecs\\win32-g++","-isystem","C:\\Qt\\6.9.3\\mingw_64\\include\\QtWidgets","-isystem","C:\\Qt\\6.9.3\\mingw_64\\include\\QtGui","-isystem","C:\\Qt\\6.9.3\\mingw_64\\include\\QtSql","-isystem","C:\\Qt\\Tools\\mingw1310_64\\lib\\gcc\\x86_64-w64-mingw32\\13.1.0\\include\\c++","-isystem","C:\\Qt\\Tools\\mingw1310_64\\lib\\gcc\\x86_64-w64-mingw32\\13.1.0\\include\\c++\\x86_64-w64-mingw32","-isystem","C:\\Qt\\Tools\\mingw1310_64\\lib\\gcc\\x86_64-w64-mingw32\\13.1.0\\include\\c++\\backward","-isystem","C:\\Qt\\Tools\\QtCreator\\bin\\clang\\lib\\clang\\20\\include","-isystem","C:\\Qt\\Tools\\mingw1310_64\\x86_64-w64-mingw32\\include","-fmessage-length=0","-fdiagnostics-show-note-include-stack","-fretain-comments-from-system-headers","-fmacro-backtrace-limit=0","-ferror-limit=1000","-x","c++","D:\\Projects\\QFinance2\\model\\categorie.cpp"],"directory":"D:/Projects/QFinance2/build/Desktop_Qt_6_9_3_MinGW_64_bit-Debug/.qtc_clangd","file":"D:/Projects/QFinance2/model/categorie.cpp"},{"arguments":["clang","-Wno-documentation-unknown-command","-Wno-unknown-warning-option","-Wno-unknown-pragmas","-nostdinc","-nostdinc++","-DQT_QML_DEBUG","-g","-std=gnu++17","-fdiagnostics-color=always","-fsyntax-only","-m64","--target=x86_64-w64-mingw32","-DMINGW_HAS_SECURE_API","-DQT_CORE_LIB","-DQT_GUI_LIB","-DQT_NEEDS_QMAIN","-DQT_SQL_LIB","-DQT_WIDGETS_LIB","-DUNICODE","-DWIN32","-DWIN64","-D_ENABLE_EXTENDED_ALIGNED_STORAGE","-D_UNICODE","-D_WIN64","-DQ_CREATOR_RUN","-DQT_ANNOTATE_FUNCTION(x)=__attribute__((annotate(#x)))","-IC:\\Qt\\Tools\\QtCreator\\share\\qtcreator\\cplusplus\\wrappedMingwHeaders","-IC:\\Qt\\Tools\\QtCreator\\share\\qtcreator\\cplusplus\\wrappedQtHeaders","-IC:\\Qt\\Tools\\QtCreator\\share\\qtcreator\\cplusplus\\wrappedQtHeaders\\QtCore","-ID:\\Projects\\QFinance2\\build\\Desktop_Qt_6_9_3_MinGW_64_bit-Debug\\QFinance2_autogen\\include","-isystem","C:\\Qt\\6.9.3\\mingw_64\\include\\QtCore","-isystem","C:\\Qt\\6.9.3\\mingw_64\\include","-isystem","C:\\Qt\\6.9.3\\mingw_64\\mkspecs\\win32-g++","-isystem","C:\\Qt\\6.9.3\\mingw_64\\include\\QtWidgets","-isystem","C:\\Qt\\6.9.3\\mingw_64\\include\\QtGui","-isystem","C:\\Qt\\6.9.3\\mingw_64\\include\\QtSql","-isystem","C:\\Qt\\Tools\\mingw1310_64\\lib\\gcc\\x86_64-w64-mingw32\\13.1.0\\include\\c++","-isystem","C:\\Qt\\Tools\\mingw1310_64\\lib\\gcc\\x86_64-w64-mingw32\\13.1.0\\include\\c++\\x86_64-w64-mingw32","-isystem","C:\\Qt\\Tools\\mingw1310_64\\lib\\gcc\\x86_64-w64-mingw32\\13.1.0\\include\\c++\\backward","-isystem","C:\\Qt\\Tools\\QtCreator\\bin\\clang\\lib\\clang\\20\\include","-isystem","C:\\Qt\\Tools\\mingw1310_64\\x86_64-w64-mingw32\\include","-fmessage-length=0","-fdiagnostics-show-note-include-stack","-fretain-comments-from-system-headers","-fmacro-backtrace-limit=0","-ferror-limit=1000","-x","c++","D:\\Projects\\QFinance2\\repository\\budgetrepository.cpp"],"directory":"D:/Projects/QFinance2/build/Desktop_Qt_6_9_3_MinGW_64_bit-Debug/.qtc_clangd","file":"D:/Projects/QFinance2/repository/budgetrepository.cpp"},{"arguments":["clang","-Wno-documentation-unknown-command","-Wno-unknown-warning-option","-Wno-unknown-pragmas","-nostdinc","-nostdinc++","-DQT_QML_DEBUG","-g","-std=gnu++17","-fdiagnostics-color=always","-fsyntax-only","-m64","--target=x86_64-w64-mingw32","-DMINGW_HAS_SECURE_API","-DQT_CORE_LIB","-DQT_GUI_LIB","-DQT_NEEDS_QMAIN","-DQT_SQL_LIB","-DQT_WIDGETS_LIB","-DUNICODE","-DWIN32","-DWIN64","-D_ENABLE_EXTENDED_ALIGNED_STORAGE","-D_UNICODE","-D_WIN64","-DQ_CREATOR_RUN","-DQT_ANNOTATE_FUNCTION(x)=__attribute__((annotate(#x)))","-IC:\\Qt\\Tools\\QtCreator\\share\\qtcreator\\cplusplus\\wrappedMingwHeaders","-IC:\\Qt\\Tools\\QtCreator\\share\\qtcreator\\cplusplus\\wrappedQtHeaders","-IC:\\Qt\\Tools\\QtCreator\\share\\qtcreator\\cplusplus\\wrappedQtHeaders\\QtCore","-ID:\\Projects\\QFinance2\\build\\Desktop_Qt_6_9_3_MinGW_64_bit-Debug\\QFinance2_autogen\\include","-isystem","C:\\Qt\\6.9.3\\mingw_64\\include\\QtCore","-isystem","C:\\Qt\\6.9.3\\mingw_64\\include","-isystem","C:\\Qt\\6.9.3\\mingw_64\\mkspecs\\win32-g++","-isystem","C:\\Qt\\6.9.3\\mingw_64\\include\\QtWidgets","-isystem","C:\\Qt\\6.9.3\\mingw_64\\include\\QtGui","-isystem","C:\\Qt\\6.9.3\\mingw_64\\include\\QtSql","-isystem","C:\\Qt\\Tools\\mingw1310_64\\lib\\gcc\\x86_64-w64-mingw32\\13.1.0\\include\\c++","-isystem","C:\\Qt\\Tools\\mingw1310_64\\lib\\gcc\\x86_64-w64-mingw32\\13.1.0\\include\\c++\\x86_64-w64-mingw32","-isystem","C:\\Qt\\Tools\\mingw1310_64\\lib\\gcc\\x86_64-w64-mingw32\\13.1.0\\include\\c++\\backward","-isystem","C:\\Qt\\Tools\\QtCreator\\bin\\clang\\lib\\clang\\20\\include","-isystem","C:\\Qt\\Tools\\mingw1310_64\\x86_64-w64-mingw32\\include","-fmessage-length=0","-fdiagnostics-show-note-include-stack","-fretain-comments-from-system-headers","-fmacro-backtrace-limit=0","-ferror-limit=1000","-x","c++","D:\\Projects\\QFinance2\\repository\\operationrepository.cpp"],"directory":"D:/Projects/QFinance2/build/Desktop_Qt_6_9_3_MinGW_64_bit-Debug/.qtc_clangd","file":"D:/Projects/QFinance2/repository/operationrepository.cpp"},{"arguments":["clang","-Wno-documentation-unknown-command","-Wno-unknown-warning-option","-Wno-unknown-pragmas","-nostdinc","-nostdinc++","-DQT_QML_DEBUG","-g","-std=gnu++17","-fdiagnostics-color=always","-fsyntax-only","-m64","--target=x86_64-w64-mingw32","-DMINGW_HAS_SECURE_API","-DQT_CORE_LIB","-DQT_GUI_LIB","-DQT_NEEDS_QMAIN","-DQT_SQL_LIB","-DQT_WIDGETS_LIB","-DUNICODE","-DWIN32","-DWIN64","-D_ENABLE_EXTENDED_ALIGNED_STORAGE","-D_UNICODE","-D_WIN64","-DQ_CREATOR_RUN","-DQT_ANNOTATE_FUNCTION(x)=__attribute__((annotate(#x)))","-IC:\\Qt\\Tools\\QtCreator\\share\\qtcreator\\cplusplus\\wrappedMingwHeaders","-IC:\\Qt\\Tools\\QtCreator\\share\\qtcreator\\cplusplus\\wrappedQtHeaders","-IC:\\Qt\\Tools\\QtCreator\\share\\qtcreator\\cplusplus\\wrappedQtHeaders\\QtCore","-ID:\\Projects\\QFinance2\\build\\Desktop_Qt_6_9_3_MinGW_64_bit-Debug\\QFinance2_autogen\\include","-isystem","C:\\Qt\\6.9.3\\mingw_64\\include\\QtCore","-isystem","C:\\Qt\\6.9.3\\mingw_64\\include","-isystem","C:\\Qt\\6.9.3\\mingw_64\\mkspecs\\win32-g++","-isystem","C:\\Qt\\6.9.3\\mingw_64\\include\\QtWidgets","-isystem","C:\\Qt\\6.9.3\\mingw_64\\include\\QtGui","-isystem","C:\\Qt\\6.9.3\\mingw_64\\include\\QtSql","-isystem","C:\\Qt\\Tools\\mingw1310_64\\lib\\gcc\\x86_64-w64-mingw32\\13.1.0\\include\\c++","-isystem","C:\\Qt\\Tools\\mingw1310_64\\lib\\gcc\\x86_64-w64-mingw32\\13.1.0\\include\\c++\\x86_64-w64-mingw32","-isystem","C:\\Qt\\Tools\\mingw1310_64\\lib\\gcc\\x86_64-w64-mingw32\\13.1.0\\include\\c++\\backward","-isystem","C:\\Qt\\Tools\\QtCreator\\bin\\clang\\lib\\clang\\20\\include","-isystem","C:\\Qt\\Tools\\mingw1310_64\\x86_64-w64-mingw32\\include","-fmessage-length=0","-fdiagnostics-show-note-include-stack","-fretain-comments-from-system-headers","-fmacro-backtrace-limit=0","-ferror-limit=1000","-x","c++","D:\\Projects\\QFinance2\\model\\Operation.cpp"],"directory":"D:/Projects/QFinance2/build/Desktop_Qt_6_9_3_MinGW_64_bit-Debug/.qtc_clangd","file":"D:/Projects/QFinance2/model/Operation.cpp"},{"arguments":["clang","-Wno-documentation-unknown-command","-Wno-unknown-warning-option","-Wno-unknown-pragmas","-nostdinc","-nostdinc++","-DQT_QML_DEBUG","-g","-std=gnu++17","-fdiagnostics-color=always","-fsyntax-only","-m64","--target=x86_64-w64-mingw32","-DMINGW_HAS_SECURE_API","-DQT_CORE_LIB","-DQT_GUI_LIB","-DQT_NEEDS_QMAIN","-DQT_SQL_LIB","-DQT_WIDGETS_LIB","-DUNICODE","-DWIN32","-DWIN64","-D_ENABLE_EXTENDED_ALIGNED_STORAGE","-D_UNICODE","-D_WIN64","-DQ_CREATOR_RUN","-DQT_ANNOTATE_FUNCTION(x)=__attribute__((annotate(#x)))","-IC:\\Qt\\Tools\\QtCreator\\share\\qtcreator\\cplusplus\\wrappedMingwHeaders","-IC:\\Qt\\Tools\\QtCreator\\share\\qtcreator\\cplusplus\\wrappedQtHeaders","-IC:\\Qt\\Tools\\QtCreator\\share\\qtcreator\\cplusplus\\wrappedQtHeaders\\QtCore","-ID:\\Projects\\QFinance2\\build\\Desktop_Qt_6_9_3_MinGW_64_bit-Debug\\QFinance2_autogen\\include","-isystem","C:\\Qt\\6.9.3\\mingw_64\\include\\QtCore","-isystem","C:\\Qt\\6.9.3\\mingw_64\\include","-isystem","C:\\Qt\\6.9.3\\mingw_64\\mkspecs\\win32-g++","-isystem","C:\\Qt\\6.9.3\\mingw_64\\include\\QtWidgets","-isystem","C:\\Qt\\6.9.3\\mingw_64\\include\\QtGui","-isystem","C:\\Qt\\6.9.3\\mingw_64\\include\\QtSql","-isystem","C:\\Qt\\Tools\\mingw1310_64\\lib\\gcc\\x86_64-w64-mingw32\\13.1.0\\include\\c++","-isystem","C:\\Qt\\Tools\\mingw1310_64\\lib\\gcc\\x86_64-w64-mingw32\\13.1.0\\include\\c++\\x86_64-w64-mingw32","-isystem","C:\\Qt\\Tools\\mingw1310_64\\lib\\gcc\\x86_64-w64-mingw32\\13.1.0\\include\\c++\\backward","-isystem","C:\\Qt\\Tools\\QtCreator\\bin\\clang\\lib\\clang\\20\\include","-isystem","C:\\Qt\\Tools\\mingw1310_64\\x86_64-w64-mingw32\\include","-fmessage-length=0","-fdiagnostics-show-note-include-stack","-fretain-comments-from-system-headers","-fmacro-backtrace-limit=0","-ferror-limit=1000","-x","c++-header","D:\\Projects\\QFinance2\\mainwindow.h"],"directory":"D:/Projects/QFinance2/build/Desktop_Qt_6_9_3_MinGW_64_bit-Debug/.qtc_clangd","file":"D:/Projects/QFinance2/mainwindow.h"},{"arguments":["clang","-Wno-documentation-unknown-command","-Wno-unknown-warning-option","-Wno-unknown-pragmas","-nostdinc","-nostdinc++","-DQT_QML_DEBUG","-g","-std=gnu++17","-fdiagnostics-color=always","-fsyntax-only","-m64","--target=x86_64-w64-mingw32","-DMINGW_HAS_SECURE_API","-DQT_CORE_LIB","-DQT_GUI_LIB","-DQT_NEEDS_QMAIN","-DQT_SQL_LIB","-DQT_WIDGETS_LIB","-DUNICODE","-DWIN32","-DWIN64","-D_ENABLE_EXTENDED_ALIGNED_STORAGE","-D_UNICODE","-D_WIN64","-DQ_CREATOR_RUN","-DQT_ANNOTATE_FUNCTION(x)=__attribute__((annotate(#x)))","-IC:\\Qt\\Tools\\QtCreator\\share\\qtcreator\\cplusplus\\wrappedMingwHeaders","-IC:\\Qt\\Tools\\QtCreator\\share\\qtcreator\\cplusplus\\wrappedQtHeaders","-IC:\\Qt\\Tools\\QtCreator\\share\\qtcreator\\cplusplus\\wrappedQtHeaders\\QtCore","-ID:\\Projects\\QFinance2\\build\\Desktop_Qt_6_9_3_MinGW_64_bit-Debug\\QFinance2_autogen\\include","-isystem","C:\\Qt\\6.9.3\\mingw_64\\include\\QtCore","-isystem","C:\\Qt\\6.9.3\\mingw_64\\include","-isystem","C:\\Qt\\6.9.3\\mingw_64\\mkspecs\\win32-g++","-isystem","C:\\Qt\\6.9.3\\mingw_64\\include\\QtWidgets","-isystem","C:\\Qt\\6.9.3\\mingw_64\\include\\QtGui","-isystem","C:\\Qt\\6.9.3\\mingw_64\\include\\QtSql","-isystem","C:\\Qt\\Tools\\mingw1310_64\\lib\\gcc\\x86_64-w64-mingw32\\13.1.0\\include\\c++","-isystem","C:\\Qt\\Tools\\mingw1310_64\\lib\\gcc\\x86_64-w64-mingw32\\13.1.0\\include\\c++\\x86_64-w64-mingw32","-isystem","C:\\Qt\\Tools\\mingw1310_64\\lib\\gcc\\x86_64-w64-mingw32\\13.1.0\\include\\c++\\backward","-isystem","C:\\Qt\\Tools\\QtCreator\\bin\\clang\\lib\\clang\\20\\include","-isystem","C:\\Qt\\Tools\\mingw1310_64\\x86_64-w64-mingw32\\include","-fmessage-length=0","-fdiagnostics-show-note-include-stack","-fretain-comments-from-system-headers","-fmacro-backtrace-limit=0","-ferror-limit=1000","-x","c++-header","D:\\Projects\\QFinance2\\database\\databasemanager.h"],"directory":"D:/Projects/QFinance2/build/Desktop_Qt_6_9_3_MinGW_64_bit-Debug/.qtc_clangd","file":"D:/Projects/QFinance2/database/databasemanager.h"},{"arguments":["clang","-Wno-documentation-unknown-command","-Wno-unknown-warning-option","-Wno-unknown-pragmas","-nostdinc","-nostdinc++","-DQT_QML_DEBUG","-g","-std=gnu++17","-fdiagnostics-color=always","-fsyntax-only","-m64","--target=x86_64-w64-mingw32","-DMINGW_HAS_SECURE_API","-DQT_CORE_LIB","-DQT_GUI_LIB","-DQT_NEEDS_QMAIN","-DQT_SQL_LIB","-DQT_WIDGETS_LIB","-DUNICODE","-DWIN32","-DWIN64","-D_ENABLE_EXTENDED_ALIGNED_STORAGE","-D_UNICODE","-D_WIN64","-DQ_CREATOR_RUN","-DQT_ANNOTATE_FUNCTION(x)=__attribute__((annotate(#x)))","-IC:\\Qt\\Tools\\QtCreator\\share\\qtcreator\\cplusplus\\wrappedMingwHeaders","-IC:\\Qt\\Tools\\QtCreator\\share\\qtcreator\\cplusplus\\wrappedQtHeaders","-IC:\\Qt\\Tools\\QtCreator\\share\\qtcreator\\cplusplus\\wrappedQtHeaders\\QtCore","-ID:\\Projects\\QFinance2\\build\\Desktop_Qt_6_9_3_MinGW_64_bit-Debug\\QFinance2_autogen\\include","-isystem","C:\\Qt\\6.9.3\\mingw_64\\include\\QtCore","-isystem","C:\\Qt\\6.9.3\\mingw_64\\include","-isystem","C:\\Qt\\6.9.3\\mingw_64\\mkspecs\\win32-g++","-isystem","C:\\Qt\\6.9.3\\mingw_64\\include\\QtWidgets","-isystem","C:\\Qt\\6.9.3\\mingw_64\\include\\QtGui","-isystem","C:\\Qt\\6.9.3\\mingw_64\\include\\QtSql","-isystem","C:\\Qt\\Tools\\mingw1310_64\\lib\\gcc\\x86_64-w64-mingw32\\13.1.0\\include\\c++","-isystem","C:\\Qt\\Tools\\mingw1310_64\\lib\\gcc\\x86_64-w64-mingw32\\13.1.0\\include\\c++\\x86_64-w64-mingw32","-isystem","C:\\Qt\\Tools\\mingw1310_64\\lib\\gcc\\x86_64-w64-mingw32\\13.1.0\\include\\c++\\backward","-isystem","C:\\Qt\\Tools\\QtCreator\\bin\\clang\\lib\\clang\\20\\include","-isystem","C:\\Qt\\Tools\\mingw1310_64\\x86_64-w64-mingw32\\include","-fmessage-length=0","-fdiagnostics-show-note-include-stack","-fretain-comments-from-system-headers","-fmacro-backtrace-limit=0","-ferror-limit=1000","-x","c++-header","D:\\Projects\\QFinance2\\model\\utilisateur.h"],"directory":"D:/Projects/QFinance2/build/Desktop_Qt_6_9_3_MinGW_64_bit-Debug/.qtc_clangd","file":"D:/Projects/QFinance2/model/utilisateur.h"},{"arguments":["clang","-Wno-documentation-unknown-command","-Wno-unknown-warning-option","-Wno-unknown-pragmas","-nostdinc","-nostdinc++","-DQT_QML_DEBUG","-g","-std=gnu++17","-fdiagnostics-color=always","-fsyntax-only","-m64","--target=x86_64-w64-mingw32","-DMINGW_HAS_SECURE_API","-DQT_CORE_LIB","-DQT_GUI_LIB","-DQT_NEEDS_QMAIN","-DQT_SQL_LIB","-DQT_WIDGETS_LIB","-DUNICODE","-DWIN32","-DWIN64","-D_ENABLE_EXTENDED_ALIGNED_STORAGE","-D_UNICODE","-D_WIN64","-DQ_CREATOR_RUN","-DQT_ANNOTATE_FUNCTION(x)=__attribute__((annotate(#x)))","-IC:\\Qt\\Tools\\QtCreator\\share\\qtcreator\\cplusplus\\wrappedMingwHeaders","-IC:\\Qt\\Tools\\QtCreator\\share\\qtcreator\\cplusplus\\wrappedQtHeaders","-IC:\\Qt\\Tools\\QtCreator\\share\\qtcreator\\cplusplus\\wrappedQtHeaders\\QtCore","-ID:\\Projects\\QFinance2\\build\\Desktop_Qt_6_9_3_MinGW_64_bit-Debug\\QFinance2_autogen\\include","-isystem","C:\\Qt\\6.9.3\\mingw_64\\include\\QtCore","-isystem","C:\\Qt\\6.9.3\\mingw_64\\include","-isystem","C:\\Qt\\6.9.3\\mingw_64\\mkspecs\\win32-g++","-isystem","C:\\Qt\\6.9.3\\mingw_64\\include\\QtWidgets","-isystem","C:\\Qt\\6.9.3\\mingw_64\\include\\QtGui","-isystem","C:\\Qt\\6.9.3\\mingw_64\\include\\QtSql","-isystem","C:\\Qt\\Tools\\mingw1310_64\\lib\\gcc\\x86_64-w64-mingw32\\13.1.0\\include\\c++","-isystem","C:\\Qt\\Tools\\mingw1310_64\\lib\\gcc\\x86_64-w64-mingw32\\13.1.0\\include\\c++\\x86_64-w64-mingw32","-isystem","C:\\Qt\\Tools\\mingw1310_64\\lib\\gcc\\x86_64-w64-mingw32\\13.1.0\\include\\c++\\backward","-isystem","C:\\Qt\\Tools\\QtCreator\\bin\\clang\\lib\\clang\\20\\include","-isystem","C:\\Qt\\Tools\\mingw1310_64\\x86_64-w64-mingw32\\include","-fmessage-length=0","-fdiagnostics-show-note-include-stack","-fretain-comments-from-system-headers","-fmacro-backtrace-limit=0","-ferror-limit=1000","-x","c++-header","D:\\Projects\\QFinance2\\model\\compte.h"],"directory":"D:/Projects/QFinance2/build/Desktop_Qt_6_9_3_MinGW_64_bit-Debug/.qtc_clangd","file":"D:/Projects/QFinance2/model/compte.h"},{"arguments":["clang","-Wno-documentation-unknown-command","-Wno-unknown-warning-option","-Wno-unknown-pragmas","-nostdinc","-nostdinc++","-DQT_QML_DEBUG","-g","-std=gnu++17","-fdiagnostics-color=always","-fsyntax-only","-m64","--target=x86_64-w64-mingw32","-DMINGW_HAS_SECURE_API","-DQT_CORE_LIB","-DQT_GUI_LIB","-DQT_NEEDS_QMAIN","-DQT_SQL_LIB","-DQT_WIDGETS_LIB","-DUNICODE","-DWIN32","-DWIN64","-D_ENABLE_EXTENDED_ALIGNED_STORAGE","-D_UNICODE","-D_WIN64","-DQ_CREATOR_RUN","-DQT_ANNOTATE_FUNCTION(x)=__attribute__((annotate(#x)))","-IC:\\Qt\\Tools\\QtCreator\\share\\qtcreator\\cplusplus\\wrappedMingwHeaders","-IC:\\Qt\\Tools\\QtCreator\\share\\qtcreator\\cplusplus\\wrappedQtHeaders","-IC:\\Qt\\Tools\\QtCreator\\share\\qtcreator\\cplusplus\\wrappedQtHeaders\\QtCore","-ID:\\Projects\\QFinance2\\build\\Desktop_Qt_6_9_3_MinGW_64_bit-Debug\\QFinance2_autogen\\include","-isystem","C:\\Qt\\6.9.3\\mingw_64\\include\\QtCore","-isystem","C:\\Qt\\6.9.3\\mingw_64\\include","-isystem","C:\\Qt\\6.9.3\\mingw_64\\mkspecs\\win32-g++","-isystem","C:\\Qt\\6.9.3\\mingw_64\\include\\QtWidgets","-isystem","C:\\Qt\\6.9.3\\mingw_64\\include\\QtGui","-isystem","C:\\Qt\\6.9.3\\mingw_64\\include\\QtSql","-isystem","C:\\Qt\\Tools\\mingw1310_64\\lib\\gcc\\x86_64-w64-mingw32\\13.1.0\\include\\c++","-isystem","C:\\Qt\\Tools\\mingw1310_64\\lib\\gcc\\x86_64-w64-mingw32\\13.1.0\\include\\c++\\x86_64-w64-mingw32","-isystem","C:\\Qt\\Tools\\mingw1310_64\\lib\\gcc\\x86_64-w64-mingw32\\13.1.0\\include\\c++\\backward","-isystem","C:\\Qt\\Tools\\QtCreator\\bin\\clang\\lib\\clang\\20\\include","-isystem","C:\\Qt\\Tools\\mingw1310_64\\x86_64-w64-mingw32\\include","-fmessage-length=0","-fdiagnostics-show-note-include-stack","-fretain-comments-from-system-headers","-fmacro-backtrace-limit=0","-ferror-limit=1000","-x","c++-header","D:\\Projects\\QFinance2\\model\\comptecourant.h"],"directory":"D:/Projects/QFinance2/build/Desktop_Qt_6_9_3_MinGW_64_bit-Debug/.qtc_clangd","file":"D:/Projects/QFinance2/model/comptecourant.h"},{"arguments":["clang","-Wno-documentation-unknown-command","-Wno-unknown-warning-option","-Wno-unknown-pragmas","-nostdinc","-nostdinc++","-DQT_QML_DEBUG","-g","-std=gnu++17","-fdiagnostics-color=always","-fsyntax-only","-m64","--target=x86_64-w64-mingw32","-DMINGW_HAS_SECURE_API","-DQT_CORE_LIB","-DQT_GUI_LIB","-DQT_NEEDS_QMAIN","-DQT_SQL_LIB","-DQT_WIDGETS_LIB","-DUNICODE","-DWIN32","-DWIN64","-D_ENABLE_EXTENDED_ALIGNED_STORAGE","-D_UNICODE","-D_WIN64","-DQ_CREATOR_RUN","-DQT_ANNOTATE_FUNCTION(x)=__attribute__((annotate(#x)))","-IC:\\Qt\\Tools\\QtCreator\\share\\qtcreator\\cplusplus\\wrappedMingwHeaders","-IC:\\Qt\\Tools\\QtCreator\\share\\qtcreator\\cplusplus\\wrappedQtHeaders","-IC:\\Qt\\Tools\\QtCreator\\share\\qtcreator\\cplusplus\\wrappedQtHeaders\\QtCore","-ID:\\Projects\\QFinance2\\build\\Desktop_Qt_6_9_3_MinGW_64_bit-Debug\\QFinance2_autogen\\include","-isystem","C:\\Qt\\6.9.3\\mingw_64\\include\\QtCore","-isystem","C:\\Qt\\6.9.3\\mingw_64\\include","-isystem","C:\\Qt\\6.9.3\\mingw_64\\mkspecs\\win32-g++","-isystem","C:\\Qt\\6.9.3\\mingw_64\\include\\QtWidgets","-isystem","C:\\Qt\\6.9.3\\mingw_64\\include\\QtGui","-isystem","C:\\Qt\\6.9.3\\mingw_64\\include\\QtSql","-isystem","C:\\Qt\\Tools\\mingw1310_64\\lib\\gcc\\x86_64-w64-mingw32\\13.1.0\\include\\c++","-isystem","C:\\Qt\\Tools\\mingw1310_64\\lib\\gcc\\x86_64-w64-mingw32\\13.1.0\\include\\c++\\x86_64-w64-mingw32","-isystem","C:\\Qt\\Tools\\mingw1310_64\\lib\\gcc\\x86_64-w64-mingw32\\13.1.0\\include\\c++\\backward","-isystem","C:\\Qt\\Tools\\QtCreator\\bin\\clang\\lib\\clang\\20\\include","-isystem","C:\\Qt\\Tools\\mingw1310_64\\x86_64-w64-mingw32\\include","-fmessage-length=0","-fdiagnostics-show-note-include-stack","-fretain-comments-from-system-headers","-fmacro-backtrace-limit=0","-ferror-limit=1000","-x","c++-header","D:\\Projects\\QFinance2\\model\\compteepargne.h"],"directory":"D:/Projects/QFinance2/build/Desktop_Qt_6_9_3_MinGW_64_bit-Debug/.qtc_clangd","file":"D:/Projects/QFinance2/model/compteepargne.h"},{"arguments":["clang","-Wno-documentation-unknown-command","-Wno-unknown-warning-option","-Wno-unknown-pragmas","-nostdinc","-nostdinc++","-DQT_QML_DEBUG","-g","-std=gnu++17","-fdiagnostics-color=always","-fsyntax-only","-m64","--target=x86_64-w64-mingw32","-DMINGW_HAS_SECURE_API","-DQT_CORE_LIB","-DQT_GUI_LIB","-DQT_NEEDS_QMAIN","-DQT_SQL_LIB","-DQT_WIDGETS_LIB","-DUNICODE","-DWIN32","-DWIN64","-D_ENABLE_EXTENDED_ALIGNED_STORAGE","-D_UNICODE","-D_WIN64","-DQ_CREATOR_RUN","-DQT_ANNOTATE_FUNCTION(x)=__attribute__((annotate(#x)))","-IC:\\Qt\\Tools\\QtCreator\\share\\qtcreator\\cplusplus\\wrappedMingwHeaders","-IC:\\Qt\\Tools\\QtCreator\\share\\qtcreator\\cplusplus\\wrappedQtHeaders","-IC:\\Qt\\Tools\\QtCreator\\share\\qtcreator\\cplusplus\\wrappedQtHeaders\\QtCore","-ID:\\Projects\\QFinance2\\build\\Desktop_Qt_6_9_3_MinGW_64_bit-Debug\\QFinance2_autogen\\include","-isystem","C:\\Qt\\6.9.3\\mingw_64\\include\\QtCore","-isystem","C:\\Qt\\6.9.3\\mingw_64\\include","-isystem","C:\\Qt\\6.9.3\\mingw_64\\mkspecs\\win32-g++","-isystem","C:\\Qt\\6.9.3\\mingw_64\\include\\QtWidgets","-isystem","C:\\Qt\\6.9.3\\mingw_64\\include\\QtGui","-isystem","C:\\Qt\\6.9.3\\mingw_64\\include\\QtSql","-isystem","C:\\Qt\\Tools\\mingw1310_64\\lib\\gcc\\x86_64-w64-mingw32\\13.1.0\\include\\c++","-isystem","C:\\Qt\\Tools\\mingw1310_64\\lib\\gcc\\x86_64-w64-mingw32\\13.1.0\\include\\c++\\x86_64-w64-mingw32","-isystem","C:\\Qt\\Tools\\mingw1310_64\\lib\\gcc\\x86_64-w64-mingw32\\13.1.0\\include\\c++\\backward","-isystem","C:\\Qt\\Tools\\QtCreator\\bin\\clang\\lib\\clang\\20\\include","-isystem","C:\\Qt\\Tools\\mingw1310_64\\x86_64-w64-mingw32\\include","-fmessage-length=0","-fdiagnostics-show-note-include-stack","-fretain-comments-from-system-headers","-fmacro-backtrace-limit=0","-ferror-limit=1000","-x","c++-header","D:\\Projects\\QFinance2\\model\\operation.h"],"directory":"D:/Projects/QFinance2/build/Desktop_Qt_6_9_3_MinGW_64_bit-Debug/.qtc_clangd","file":"D:/Projects/QFinance2/model/operation.h"},{"arguments":["clang","-Wno-documentation-unknown-command","-Wno-unknown-warning-option","-Wno-unknown-pragmas","-nostdinc","-nostdinc++","-DQT_QML_DEBUG","-g","-std=gnu++17","-fdiagnostics-color=always","-fsyntax-only","-m64","--target=x86_64-w64-mingw32","-DMINGW_HAS_SECURE_API","-DQT_CORE_LIB","-DQT_GUI_LIB","-DQT_NEEDS_QMAIN","-DQT_SQL_LIB","-DQT_WIDGETS_LIB","-DUNICODE","-DWIN32","-DWIN64","-D_ENABLE_EXTENDED_ALIGNED_STORAGE","-D_UNICODE","-D_WIN64","-DQ_CREATOR_RUN","-DQT_ANNOTATE_FUNCTION(x)=__attribute__((annotate(#x)))","-IC:\\Qt\\Tools\\QtCreator\\share\\qtcreator\\cplusplus\\wrappedMingwHeaders","-IC:\\Qt\\Tools\\QtCreator\\share\\qtcreator\\cplusplus\\wrappedQtHeaders","-IC:\\Qt\\Tools\\QtCreator\\share\\qtcreator\\cplusplus\\wrappedQtHeaders\\QtCore","-ID:\\Projects\\QFinance2\\build\\Desktop_Qt_6_9_3_MinGW_64_bit-Debug\\QFinance2_autogen\\include","-isystem","C:\\Qt\\6.9.3\\mingw_64\\include\\QtCore","-isystem","C:\\Qt\\6.9.3\\mingw_64\\include","-isystem","C:\\Qt\\6.9.3\\mingw_64\\mkspecs\\win32-g++","-isystem","C:\\Qt\\6.9.3\\mingw_64\\include\\QtWidgets","-isystem","C:\\Qt\\6.9.3\\mingw_64\\include\\QtGui","-isystem","C:\\Qt\\6.9.3\\mingw_64\\include\\QtSql","-isystem","C:\\Qt\\Tools\\mingw1310_64\\lib\\gcc\\x86_64-w64-mingw32\\13.1.0\\include\\c++","-isystem","C:\\Qt\\Tools\\mingw1310_64\\lib\\gcc\\x86_64-w64-mingw32\\13.1.0\\include\\c++\\x86_64-w64-mingw32","-isystem","C:\\Qt\\Tools\\mingw1310_64\\lib\\gcc\\x86_64-w64-mingw32\\13.1.0\\include\\c++\\backward","-isystem","C:\\Qt\\Tools\\QtCreator\\bin\\clang\\lib\\clang\\20\\include","-isystem","C:\\Qt\\Tools\\mingw1310_64\\x86_64-w64-mingw32\\include","-fmessage-length=0","-fdiagnostics-show-note-include-stack","-fretain-comments-from-system-headers","-fmacro-backtrace-limit=0","-ferror-limit=1000","-x","c++-header","D:\\Projects\\QFinance2\\model\\transfert.h"],"directory":"D:/Projects/QFinance2/build/Desktop_Qt_6_9_3_MinGW_64_bit-Debug/.qtc_clangd","file":"D:/Projects/QFinance2/model/transfert.h"},{"arguments":["clang","-Wno-documentation-unknown-command","-Wno-unknown-warning-option","-Wno-unknown-pragmas","-nostdinc","-nostdinc++","-DQT_QML_DEBUG","-g","-std=gnu++17","-fdiagnostics-color=always","-fsyntax-only","-m64","--target=x86_64-w64-mingw32","-DMINGW_HAS_SECURE_API","-DQT_CORE_LIB","-DQT_GUI_LIB","-DQT_NEEDS_QMAIN","-DQT_SQL_LIB","-DQT_WIDGETS_LIB","-DUNICODE","-DWIN32","-DWIN64","-D_ENABLE_EXTENDED_ALIGNED_STORAGE","-D_UNICODE","-D_WIN64","-DQ_CREATOR_RUN","-DQT_ANNOTATE_FUNCTION(x)=__attribute__((annotate(#x)))","-IC:\\Qt\\Tools\\QtCreator\\share\\qtcreator\\cplusplus\\wrappedMingwHeaders","-IC:\\Qt\\Tools\\QtCreator\\share\\qtcreator\\cplusplus\\wrappedQtHeaders","-IC:\\Qt\\Tools\\QtCreator\\share\\qtcreator\\cplusplus\\wrappedQtHeaders\\QtCore","-ID:\\Projects\\QFinance2\\build\\Desktop_Qt_6_9_3_MinGW_64_bit-Debug\\QFinance2_autogen\\include","-isystem","C:\\Qt\\6.9.3\\mingw_64\\include\\QtCore","-isystem","C:\\Qt\\6.9.3\\mingw_64\\include","-isystem","C:\\Qt\\6.9.3\\mingw_64\\mkspecs\\win32-g++","-isystem","C:\\Qt\\6.9.3\\mingw_64\\include\\QtWidgets","-isystem","C:\\Qt\\6.9.3\\mingw_64\\include\\QtGui","-isystem","C:\\Qt\\6.9.3\\mingw_64\\include\\QtSql","-isystem","C:\\Qt\\Tools\\mingw1310_64\\lib\\gcc\\x86_64-w64-mingw32\\13.1.0\\include\\c++","-isystem","C:\\Qt\\Tools\\mingw1310_64\\lib\\gcc\\x86_64-w64-mingw32\\13.1.0\\include\\c++\\x86_64-w64-mingw32","-isystem","C:\\Qt\\Tools\\mingw1310_64\\lib\\gcc\\x86_64-w64-mingw32\\13.1.0\\include\\c++\\backward","-isystem","C:\\Qt\\Tools\\QtCreator\\bin\\clang\\lib\\clang\\20\\include","-isystem","C:\\Qt\\Tools\\mingw1310_64\\x86_64-w64-mingw32\\include","-fmessage-length=0","-fdiagnostics-show-note-include-stack","-fretain-comments-from-system-headers","-fmacro-backtrace-limit=0","-ferror-limit=1000","-x","c++-header","D:\\Projects\\QFinance2\\repository\\compterepository.h"],"directory":"D:/Projects/QFinance2/build/Desktop_Qt_6_9_3_MinGW_64_bit-Debug/.qtc_clangd","file":"D:/Projects/QFinance2/repository/compterepository.h"},{"arguments":["clang","-Wno-documentation-unknown-command","-Wno-unknown-warning-option","-Wno-unknown-pragmas","-nostdinc","-nostdinc++","-DQT_QML_DEBUG","-g","-std=gnu++17","-fdiagnostics-color=always","-fsyntax-only","-m64","--target=x86_64-w64-mingw32","-DMINGW_HAS_SECURE_API","-DQT_CORE_LIB","-DQT_GUI_LIB","-DQT_NEEDS_QMAIN","-DQT_SQL_LIB","-DQT_WIDGETS_LIB","-DUNICODE","-DWIN32","-DWIN64","-D_ENABLE_EXTENDED_ALIGNED_STORAGE","-D_UNICODE","-D_WIN64","-DQ_CREATOR_RUN","-DQT_ANNOTATE_FUNCTION(x)=__attribute__((annotate(#x)))","-IC:\\Qt\\Tools\\QtCreator\\share\\qtcreator\\cplusplus\\wrappedMingwHeaders","-IC:\\Qt\\Tools\\QtCreator\\share\\qtcreator\\cplusplus\\wrappedQtHeaders","-IC:\\Qt\\Tools\\QtCreator\\share\\qtcreator\\cplusplus\\wrappedQtHeaders\\QtCore","-ID:\\Projects\\QFinance2\\build\\Desktop_Qt_6_9_3_MinGW_64_bit-Debug\\QFinance2_autogen\\include","-isystem","C:\\Qt\\6.9.3\\mingw_64\\include\\QtCore","-isystem","C:\\Qt\\6.9.3\\mingw_64\\include","-isystem","C:\\Qt\\6.9.3\\mingw_64\\mkspecs\\win32-g++","-isystem","C:\\Qt\\6.9.3\\mingw_64\\include\\QtWidgets","-isystem","C:\\Qt\\6.9.3\\mingw_64\\include\\QtGui","-isystem","C:\\Qt\\6.9.3\\mingw_64\\include\\QtSql","-isystem","C:\\Qt\\Tools\\mingw1310_64\\lib\\gcc\\x86_64-w64-mingw32\\13.1.0\\include\\c++","-isystem","C:\\Qt\\Tools\\mingw1310_64\\lib\\gcc\\x86_64-w64-mingw32\\13.1.0\\include\\c++\\x86_64-w64-mingw32","-isystem","C:\\Qt\\Tools\\mingw1310_64\\lib\\gcc\\x86_64-w64-mingw32\\13.1.0\\include\\c++\\backward","-isystem","C:\\Qt\\Tools\\QtCreator\\bin\\clang\\lib\\clang\\20\\include","-isystem","C:\\Qt\\Tools\\mingw1310_64\\x86_64-w64-mingw32\\include","-fmessage-length=0","-fdiagnostics-show-note-include-stack","-fretain-comments-from-system-headers","-fmacro-backtrace-limit=0","-ferror-limit=1000","-x","c++-header","D:\\Projects\\QFinance2\\repository\\transfertrepository.h"],"directory":"D:/Projects/QFinance2/build/Desktop_Qt_6_9_3_MinGW_64_bit-Debug/.qtc_clangd","file":"D:/Projects/QFinance2/repository/transfertrepository.h"},{"arguments":["clang","-Wno-documentation-unknown-command","-Wno-unknown-warning-option","-Wno-unknown-pragmas","-nostdinc","-nostdinc++","-DQT_QML_DEBUG","-g","-std=gnu++17","-fdiagnostics-color=always","-fsyntax-only","-m64","--target=x86_64-w64-mingw32","-DMINGW_HAS_SECURE_API","-DQT_CORE_LIB","-DQT_GUI_LIB","-DQT_NEEDS_QMAIN","-DQT_SQL_LIB","-DQT_WIDGETS_LIB","-DUNICODE","-DWIN32","-DWIN64","-D_ENABLE_EXTENDED_ALIGNED_STORAGE","-D_UNICODE","-D_WIN64","-DQ_CREATOR_RUN","-DQT_ANNOTATE_FUNCTION(x)=__attribute__((annotate(#x)))","-IC:\\Qt\\Tools\\QtCreator\\share\\qtcreator\\cplusplus\\wrappedMingwHeaders","-IC:\\Qt\\Tools\\QtCreator\\share\\qtcreator\\cplusplus\\wrappedQtHeaders","-IC:\\Qt\\Tools\\QtCreator\\share\\qtcreator\\cplusplus\\wrappedQtHeaders\\QtCore","-ID:\\Projects\\QFinance2\\build\\Desktop_Qt_6_9_3_MinGW_64_bit-Debug\\QFinance2_autogen\\include","-isystem","C:\\Qt\\6.9.3\\mingw_64\\include\\QtCore","-isystem","C:\\Qt\\6.9.3\\mingw_64\\include","-isystem","C:\\Qt\\6.9.3\\mingw_64\\mkspecs\\win32-g++","-isystem","C:\\Qt\\6.9.3\\mingw_64\\include\\QtWidgets","-isystem","C:\\Qt\\6.9.3\\mingw_64\\include\\QtGui","-isystem","C:\\Qt\\6.9.3\\mingw_64\\include\\QtSql","-isystem","C:\\Qt\\Tools\\mingw1310_64\\lib\\gcc\\x86_64-w64-mingw32\\13.1.0\\include\\c++","-isystem","C:\\Qt\\Tools\\mingw1310_64\\lib\\gcc\\x86_64-w64-mingw32\\13.1.0\\include\\c++\\x86_64-w64-mingw32","-isystem","C:\\Qt\\Tools\\mingw1310_64\\lib\\gcc\\x86_64-w64-mingw32\\13.1.0\\include\\c++\\backward","-isystem","C:\\Qt\\Tools\\QtCreator\\bin\\clang\\lib\\clang\\20\\include","-isystem","C:\\Qt\\Tools\\mingw1310_64\\x86_64-w64-mingw32\\include","-fmessage-length=0","-fdiagnostics-show-note-include-stack","-fretain-comments-from-system-headers","-fmacro-backtrace-limit=0","-ferror-limit=1000","-x","c++-header","D:\\Projects\\QFinance2\\repository\\categorierepository.h"],"directory":"D:/Projects/QFinance2/build/Desktop_Qt_6_9_3_MinGW_64_bit-Debug/.qtc_clangd","file":"D:/Projects/QFinance2/repository/categorierepository.h"},{"arguments":["clang","-Wno-documentation-unknown-command","-Wno-unknown-warning-option","-Wno-unknown-pragmas","-nostdinc","-nostdinc++","-DQT_QML_DEBUG","-g","-std=gnu++17","-fdiagnostics-color=always","-fsyntax-only","-m64","--target=x86_64-w64-mingw32","-DMINGW_HAS_SECURE_API","-DQT_CORE_LIB","-DQT_GUI_LIB","-DQT_NEEDS_QMAIN","-DQT_SQL_LIB","-DQT_WIDGETS_LIB","-DUNICODE","-DWIN32","-DWIN64","-D_ENABLE_EXTENDED_ALIGNED_STORAGE","-D_UNICODE","-D_WIN64","-DQ_CREATOR_RUN","-DQT_ANNOTATE_FUNCTION(x)=__attribute__((annotate(#x)))","-IC:\\Qt\\Tools\\QtCreator\\share\\qtcreator\\cplusplus\\wrappedMingwHeaders","-IC:\\Qt\\Tools\\QtCreator\\share\\qtcreator\\cplusplus\\wrappedQtHeaders","-IC:\\Qt\\Tools\\QtCreator\\share\\qtcreator\\cplusplus\\wrappedQtHeaders\\QtCore","-ID:\\Projects\\QFinance2\\build\\Desktop_Qt_6_9_3_MinGW_64_bit-Debug\\QFinance2_autogen\\include","-isystem","C:\\Qt\\6.9.3\\mingw_64\\include\\QtCore","-isystem","C:\\Qt\\6.9.3\\mingw_64\\include","-isystem","C:\\Qt\\6.9.3\\mingw_64\\mkspecs\\win32-g++","-isystem","C:\\Qt\\6.9.3\\mingw_64\\include\\QtWidgets","-isystem","C:\\Qt\\6.9.3\\mingw_64\\include\\QtGui","-isystem","C:\\Qt\\6.9.3\\mingw_64\\include\\QtSql","-isystem","C:\\Qt\\Tools\\mingw1310_64\\lib\\gcc\\x86_64-w64-mingw32\\13.1.0\\include\\c++","-isystem","C:\\Qt\\Tools\\mingw1310_64\\lib\\gcc\\x86_64-w64-mingw32\\13.1.0\\include\\c++\\x86_64-w64-mingw32","-isystem","C:\\Qt\\Tools\\mingw1310_64\\lib\\gcc\\x86_64-w64-mingw32\\13.1.0\\include\\c++\\backward","-isystem","C:\\Qt\\Tools\\QtCreator\\bin\\clang\\lib\\clang\\20\\include","-isystem","C:\\Qt\\Tools\\mingw1310_64\\x86_64-w64-mingw32\\include","-fmessage-length=0","-fdiagnostics-show-note-include-stack","-fretain-comments-from-system-headers","-fmacro-backtrace-limit=0","-ferror-limit=1000","-x","c++-header","D:\\Projects\\QFinance2\\model\\categorie.h"],"directory":"D:/Projects/QFinance2/build/Desktop_Qt_6_9_3_MinGW_64_bit-Debug/.qtc_clangd","file":"D:/Projects/QFinance2/model/categorie.h"},{"arguments":["clang","-Wno-documentation-unknown-command","-Wno-unknown-warning-option","-Wno-unknown-pragmas","-nostdinc","-nostdinc++","-DQT_QML_DEBUG","-g","-std=gnu++17","-fdiagnostics-color=always","-fsyntax-only","-m64","--target=x86_64-w64-mingw32","-DMINGW_HAS_SECURE_API","-DQT_CORE_LIB","-DQT_GUI_LIB","-DQT_NEEDS_QMAIN","-DQT_SQL_LIB","-DQT_WIDGETS_LIB","-DUNICODE","-DWIN32","-DWIN64","-D_ENABLE_EXTENDED_ALIGNED_STORAGE","-D_UNICODE","-D_WIN64","-DQ_CREATOR_RUN","-DQT_ANNOTATE_FUNCTION(x)=__attribute__((annotate(#x)))","-IC:\\Qt\\Tools\\QtCreator\\share\\qtcreator\\cplusplus\\wrappedMingwHeaders","-IC:\\Qt\\Tools\\QtCreator\\share\\qtcreator\\cplusplus\\wrappedQtHeaders","-IC:\\Qt\\Tools\\QtCreator\\share\\qtcreator\\cplusplus\\wrappedQtHeaders\\QtCore","-ID:\\Projects\\QFinance2\\build\\Desktop_Qt_6_9_3_MinGW_64_bit-Debug\\QFinance2_autogen\\include","-isystem","C:\\Qt\\6.9.3\\mingw_64\\include\\QtCore","-isystem","C:\\Qt\\6.9.3\\mingw_64\\include","-isystem","C:\\Qt\\6.9.3\\mingw_64\\mkspecs\\win32-g++","-isystem","C:\\Qt\\6.9.3\\mingw_64\\include\\QtWidgets","-isystem","C:\\Qt\\6.9.3\\mingw_64\\include\\QtGui","-isystem","C:\\Qt\\6.9.3\\mingw_64\\include\\QtSql","-isystem","C:\\Qt\\Tools\\mingw1310_64\\lib\\gcc\\x86_64-w64-mingw32\\13.1.0\\include\\c++","-isystem","C:\\Qt\\Tools\\mingw1310_64\\lib\\gcc\\x86_64-w64-mingw32\\13.1.0\\include\\c++\\x86_64-w64-mingw32","-isystem","C:\\Qt\\Tools\\mingw1310_64\\lib\\gcc\\x86_64-w64-mingw32\\13.1.0\\include\\c++\\backward","-isystem","C:\\Qt\\Tools\\QtCreator\\bin\\clang\\lib\\clang\\20\\include","-isystem","C:\\Qt\\Tools\\mingw1310_64\\x86_64-w64-mingw32\\include","-fmessage-length=0","-fdiagnostics-show-note-include-stack","-fretain-comments-from-system-headers","-fmacro-backtrace-limit=0","-ferror-limit=1000","-x","c++-header","D:\\Projects\\QFinance2\\repository\\budgetrepository.h"],"directory":"D:/Projects/QFinance2/build/Desktop_Qt_6_9_3_MinGW_64_bit-Debug/.qtc_clangd","file":"D:/Projects/QFinance2/repository/budgetrepository.h"},{"arguments":["clang","-Wno-documentation-unknown-command","-Wno-unknown-warning-option","-Wno-unknown-pragmas","-nostdinc","-nostdinc++","-DQT_QML_DEBUG","-g","-std=gnu++17","-fdiagnostics-color=always","-fsyntax-only","-m64","--target=x86_64-w64-mingw32","-DMINGW_HAS_SECURE_API","-DQT_CORE_LIB","-DQT_GUI_LIB","-DQT_NEEDS_QMAIN","-DQT_SQL_LIB","-DQT_WIDGETS_LIB","-DUNICODE","-DWIN32","-DWIN64","-D_ENABLE_EXTENDED_ALIGNED_STORAGE","-D_UNICODE","-D_WIN64","-DQ_CREATOR_RUN","-DQT_ANNOTATE_FUNCTION(x)=__attribute__((annotate(#x)))","-IC:\\Qt\\Tools\\QtCreator\\share\\qtcreator\\cplusplus\\wrappedMingwHeaders","-IC:\\Qt\\Tools\\QtCreator\\share\\qtcreator\\cplusplus\\wrappedQtHeaders","-IC:\\Qt\\Tools\\QtCreator\\share\\qtcreator\\cplusplus\\wrappedQtHeaders\\QtCore","-ID:\\Projects\\QFinance2\\build\\Desktop_Qt_6_9_3_MinGW_64_bit-Debug\\QFinance2_autogen\\include","-isystem","C:\\Qt\\6.9.3\\mingw_64\\include\\QtCore","-isystem","C:\\Qt\\6.9.3\\mingw_64\\include","-isystem","C:\\Qt\\6.9.3\\mingw_64\\mkspecs\\win32-g++","-isystem","C:\\Qt\\6.9.3\\mingw_64\\include\\QtWidgets","-isystem","C:\\Qt\\6.9.3\\mingw_64\\include\\QtGui","-isystem","C:\\Qt\\6.9.3\\mingw_64\\include\\QtSql","-isystem","C:\\Qt\\Tools\\mingw1310_64\\lib\\gcc\\x86_64-w64-mingw32\\13.1.0\\include\\c++","-isystem","C:\\Qt\\Tools\\mingw1310_64\\lib\\gcc\\x86_64-w64-mingw32\\13.1.0\\include\\c++\\x86_64-w64-mingw32","-isystem","C:\\Qt\\Tools\\mingw1310_64\\lib\\gcc\\x86_64-w64-mingw32\\13.1.0\\include\\c++\\backward","-isystem","C:\\Qt\\Tools\\QtCreator\\bin\\clang\\lib\\clang\\20\\include","-isystem","C:\\Qt\\Tools\\mingw1310_64\\x86_64-w64-mingw32\\include","-fmessage-length=0","-fdiagnostics-show-note-include-stack","-fretain-comments-from-system-headers","-fmacro-backtrace-limit=0","-ferror-limit=1000","-x","c++-header","D:\\Projects\\QFinance2\\model\\budget.h"],"directory":"D:/Projects/QFinance2/build/Desktop_Qt_6_9_3_MinGW_64_bit-Debug/.qtc_clangd","file":"D:/Projects/QFinance2/model/budget.h"},{"arguments":["clang","-Wno-documentation-unknown-command","-Wno-unknown-warning-option","-Wno-unknown-pragmas","-nostdinc","-nostdinc++","-DQT_QML_DEBUG","-g","-std=gnu++17","-fdiagnostics-color=always","-fsyntax-only","-m64","--target=x86_64-w64-mingw32","-DMINGW_HAS_SECURE_API","-DQT_CORE_LIB","-DQT_GUI_LIB","-DQT_NEEDS_QMAIN","-DQT_SQL_LIB","-DQT_WIDGETS_LIB","-DUNICODE","-DWIN32","-DWIN64","-D_ENABLE_EXTENDED_ALIGNED_STORAGE","-D_UNICODE","-D_WIN64","-DQ_CREATOR_RUN","-DQT_ANNOTATE_FUNCTION(x)=__attribute__((annotate(#x)))","-IC:\\Qt\\Tools\\QtCreator\\share\\qtcreator\\cplusplus\\wrappedMingwHeaders","-IC:\\Qt\\Tools\\QtCreator\\share\\qtcreator\\cplusplus\\wrappedQtHeaders","-IC:\\Qt\\Tools\\QtCreator\\share\\qtcreator\\cplusplus\\wrappedQtHeaders\\QtCore","-ID:\\Projects\\QFinance2\\build\\Desktop_Qt_6_9_3_MinGW_64_bit-Debug\\QFinance2_autogen\\include","-isystem","C:\\Qt\\6.9.3\\mingw_64\\include\\QtCore","-isystem","C:\\Qt\\6.9.3\\mingw_64\\include","-isystem","C:\\Qt\\6.9.3\\mingw_64\\mkspecs\\win32-g++","-isystem","C:\\Qt\\6.9.3\\mingw_64\\include\\QtWidgets","-isystem","C:\\Qt\\6.9.3\\mingw_64\\include\\QtGui","-isystem","C:\\Qt\\6.9.3\\mingw_64\\include\\QtSql","-isystem","C:\\Qt\\Tools\\mingw1310_64\\lib\\gcc\\x86_64-w64-mingw32\\13.1.0\\include\\c++","-isystem","C:\\Qt\\Tools\\mingw1310_64\\lib\\gcc\\x86_64-w64-mingw32\\13.1.0\\include\\c++\\x86_64-w64-mingw32","-isystem","C:\\Qt\\Tools\\mingw1310_64\\lib\\gcc\\x86_64-w64-mingw32\\13.1.0\\include\\c++\\backward","-isystem","C:\\Qt\\Tools\\QtCreator\\bin\\clang\\lib\\clang\\20\\include","-isystem","C:\\Qt\\Tools\\mingw1310_64\\x86_64-w64-mingw32\\include","-fmessage-length=0","-fdiagnostics-show-note-include-stack","-fretain-comments-from-system-headers","-fmacro-backtrace-limit=0","-ferror-limit=1000","-x","c++-header","D:\\Projects\\QFinance2\\model\\Revenu.h"],"directory":"D:/Projects/QFinance2/build/Desktop_Qt_6_9_3_MinGW_64_bit-Debug/.qtc_clangd","file":"D:/Projects/QFinance2/model/Revenu.h"},{"arguments":["clang","-Wno-documentation-unknown-command","-Wno-unknown-warning-option","-Wno-unknown-pragmas","-nostdinc","-nostdinc++","-DQT_QML_DEBUG","-g","-std=gnu++17","-fdiagnostics-color=always","-fsyntax-only","-m64","--target=x86_64-w64-mingw32","-DMINGW_HAS_SECURE_API","-DQT_CORE_LIB","-DQT_GUI_LIB","-DQT_NEEDS_QMAIN","-DQT_SQL_LIB","-DQT_WIDGETS_LIB","-DUNICODE","-DWIN32","-DWIN64","-D_ENABLE_EXTENDED_ALIGNED_STORAGE","-D_UNICODE","-D_WIN64","-DQ_CREATOR_RUN","-DQT_ANNOTATE_FUNCTION(x)=__attribute__((annotate(#x)))","-IC:\\Qt\\Tools\\QtCreator\\share\\qtcreator\\cplusplus\\wrappedMingwHeaders","-IC:\\Qt\\Tools\\QtCreator\\share\\qtcreator\\cplusplus\\wrappedQtHeaders","-IC:\\Qt\\Tools\\QtCreator\\share\\qtcreator\\cplusplus\\wrappedQtHeaders\\QtCore","-ID:\\Projects\\QFinance2\\build\\Desktop_Qt_6_9_3_MinGW_64_bit-Debug\\QFinance2_autogen\\include","-isystem","C:\\Qt\\6.9.3\\mingw_64\\include\\QtCore","-isystem","C:\\Qt\\6.9.3\\mingw_64\\include","-isystem","C:\\Qt\\6.9.3\\mingw_64\\mkspecs\\win32-g++","-isystem","C:\\Qt\\6.9.3\\mingw_64\\include\\QtWidgets","-isystem","C:\\Qt\\6.9.3\\mingw_64\\include\\QtGui","-isystem","C:\\Qt\\6.9.3\\mingw_64\\include\\QtSql","-isystem","C:\\Qt\\Tools\\mingw1310_64\\lib\\gcc\\x86_64-w64-mingw32\\13.1.0\\include\\c++","-isystem","C:\\Qt\\Tools\\mingw1310_64\\lib\\gcc\\x86_64-w64-mingw32\\13.1.0\\include\\c++\\x86_64-w64-mingw32","-isystem","C:\\Qt\\Tools\\mingw1310_64\\lib\\gcc\\x86_64-w64-mingw32\\13.1.0\\include\\c++\\backward","-isystem","C:\\Qt\\Tools\\QtCreator\\bin\\clang\\lib\\clang\\20\\include","-isystem","C:\\Qt\\Tools\\mingw1310_64\\x86_64-w64-mingw32\\include","-fmessage-length=0","-fdiagnostics-show-note-include-stack","-fretain-comments-from-system-headers","-fmacro-backtrace-limit=0","-ferror-limit=1000","-x","c++-header","D:\\Projects\\QFinance2\\model\\Depense.h"],"directory":"D:/Projects/QFinance2/build/Desktop_Qt_6_9_3_MinGW_64_bit-Debug/.qtc_clangd","file":"D:/Projects/QFinance2/model/Depense.h"},{"arguments":["clang","-Wno-documentation-unknown-command","-Wno-unknown-warning-option","-Wno-unknown-pragmas","-nostdinc","-nostdinc++","-DQT_QML_DEBUG","-g","-std=gnu++17","-fdiagnostics-color=always","-fsyntax-only","-m64","--target=x86_64-w64-mingw32","-DMINGW_HAS_SECURE_API","-DQT_CORE_LIB","-DQT_GUI_LIB","-DQT_NEEDS_QMAIN","-DQT_SQL_LIB","-DQT_WIDGETS_LIB","-DUNICODE","-DWIN32","-DWIN64","-D_ENABLE_EXTENDED_ALIGNED_STORAGE","-D_UNICODE","-D_WIN64","-DQ_CREATOR_RUN","-DQT_ANNOTATE_FUNCTION(x)=__attribute__((annotate(#x)))","-IC:\\Qt\\Tools\\QtCreator\\share\\qtcreator\\cplusplus\\wrappedMingwHeaders","-IC:\\Qt\\Tools\\QtCreator\\share\\qtcreator\\cplusplus\\wrappedQtHeaders","-IC:\\Qt\\Tools\\QtCreator\\share\\qtcreator\\cplusplus\\wrappedQtHeaders\\QtCore","-ID:\\Projects\\QFinance2\\build\\Desktop_Qt_6_9_3_MinGW_64_bit-Debug\\QFinance2_autogen\\include","-isystem","C:\\Qt\\6.9.3\\mingw_64\\include\\QtCore","-isystem","C:\\Qt\\6.9.3\\mingw_64\\include","-isystem","C:\\Qt\\6.9.3\\mingw_64\\mkspecs\\win32-g++","-isystem","C:\\Qt\\6.9.3\\mingw_64\\include\\QtWidgets","-isystem","C:\\Qt\\6.9.3\\mingw_64\\include\\QtGui","-isystem","C:\\Qt\\6.9.3\\mingw_64\\include\\QtSql","-isystem","C:\\Qt\\Tools\\mingw1310_64\\lib\\gcc\\x86_64-w64-mingw32\\13.1.0\\include\\c++","-isystem","C:\\Qt\\Tools\\mingw1310_64\\lib\\gcc\\x86_64-w64-mingw32\\13.1.0\\include\\c++\\x86_64-w64-mingw32","-isystem","C:\\Qt\\Tools\\mingw1310_64\\lib\\gcc\\x86_64-w64-mingw32\\13.1.0\\include\\c++\\backward","-isystem","C:\\Qt\\Tools\\QtCreator\\bin\\clang\\lib\\clang\\20\\include","-isystem","C:\\Qt\\Tools\\mingw1310_64\\x86_64-w64-mingw32\\include","-fmessage-length=0","-fdiagnostics-show-note-include-stack","-fretain-comments-from-system-headers","-fmacro-backtrace-limit=0","-ferror-limit=1000","-x","c++-header","D:\\Projects\\QFinance2\\repository\\operationrepository.h"],"directory":"D:/Projects/QFinance2/build/Desktop_Qt_6_9_3_MinGW_64_bit-Debug/.qtc_clangd","file":"D:/Projects/QFinance2/repository/operationrepository.h"}]